json_flattener_to_csv_amazon/__init__.py
json_flattener_to_csv_amazon/flattener.py
json_flattener_to_csv_amazon-0.2.dist-info/LICENSE
json_flattener_to_csv_amazon-0.2.dist-info/METADATA
json_flattener_to_csv_amazon-0.2.dist-info/WHEEL
json_flattener_to_csv_amazon-0.2.dist-info/top_level.txt
json_flattener_to_csv_amazon-0.2.dist-info/RECORD
